sparqlx/__init__.py
sparqlx/py.typed
sparqlx/sparqlwrapper.py
sparqlx/types.py
sparqlx/utils/client_manager.py
sparqlx/utils/converters.py
sparqlx/utils/logging_hooks.py
sparqlx/utils/operation_parameters.py
sparqlx/utils/transports.py
sparqlx/utils/utils.py
sparqlx-0.9.0.dist-info/METADATA
sparqlx-0.9.0.dist-info/WHEEL
sparqlx-0.9.0.dist-info/licenses/LICENSE
sparqlx-0.9.0.dist-info/RECORD
