Metadata-Version: 2.4
Name: sparqlx
Version: 0.9.0
Summary: Add your description here
Author-email: Lukas Plank <lupl@tuta.io>
License-File: LICENSE
Requires-Python: >=3.12
Requires-Dist: httpx>=0.28.1
Requires-Dist: rdflib>=7.3.0
